Az6/Code/Incubator.v
module Incubator(
  input signed [7:0] temperature,
  input clk,
  input reset,
  output reg heater,
  output reg cooler,
  output reg [3:0] crs
  );
  
  always @(posedge clk or negedge reset) begin
    if (~reset) begin
      heater = 0;
      cooler = 0;
      crs = 4'd0;
    end
    else begin
      if (~heater && ~cooler) begin
        if ($signed(temperature) > $signed(8'd35)) begin
           heater = 0;
           cooler = 1;
           crs = 4'd4;
        end
        else if ($signed(temperature) < $signed(8'd15)) begin
           heater = 1;
           cooler = 0;
        end
      end
      else if (heater && ~cooler && $signed(temperature) > $signed(8'd30)) begin
           heater = 0;
           cooler = 0;
      end
      else if (~heater && cooler) begin
        if (crs == 4'd8 && $signed(temperature) < $signed(8'd40))
          crs = 4'd6;
        else if (crs == 4'd6 && $signed(temperature) > $signed(8'd45))
          crs = 4'd8;
        else if (crs == 4'd6 && $signed(temperature) < $signed(8'd35))
          crs = 4'd4;  
        else if (crs == 4'd4 && $signed(temperature) > $signed(8'd40))
          crs = 4'd6;
        else if (crs == 4'd4 && $signed(temperature) < $signed(8'd25)) begin
          heater = 0;
          cooler = 0;
          crs = 4'd0;
        end
      end
    end
  end
  
endmodule

Az6/Code/testbench.v
module testbench;

reg signed [7:0] temperature;
reg clk = 0;
reg reset = 0;
wire [3:0] crs;
wire heater;
wire cooler;

Incubator incubator(temperature, clk, reset, heater, cooler, crs);

initial begin
    $dumpfile("wave.vcd");
    $dumpvars(0, testbench);
    temperature = 8'd20;
    #20 reset = 1;
    #20 temperature = 8'd40;
    #20 temperature = 8'd20;
    #20 temperature = 8'd10;
    #20 reset = 0;
    #20 reset = 1;
    #20 temperature = 8'd40;
    #20 temperature = 8'd45;
    #20 temperature = 8'd50;
    #40 temperature = 8'd20;
    #100 $stop;
end

always
  #10 clk = ~clk;

endmodule

Az6/Code/wave.vcd
$date
	Wed Jul 19 00:54:27 2023
$end
$version
	ModelSim Version 10.1d
$end
$timescale
	1ps
$end
$scope module testbench $end
$var reg 8 ! temperature [7:0] $end
$var reg 1 " clk $end
$var reg 1 # reset $end
$var wire 1 $ crs [3] $end
$var wire 1 % crs [2] $end
$var wire 1 & crs [1] $end
$var wire 1 ' crs [0] $end
$var wire 1 ( heater $end
$var wire 1 ) cooler $end
$scope module incubator $end
$var wire 1 * temperature [7] $end
$var wire 1 + temperature [6] $end
$var wire 1 , temperature [5] $end
$var wire 1 - temperature [4] $end
$var wire 1 . temperature [3] $end
$var wire 1 / temperature [2] $end
$var wire 1 0 temperature [1] $end
$var wire 1 1 temperature [0] $end
$var wire 1 2 clk $end
$var wire 1 3 reset $end
$var reg 1 4 heater $end
$var reg 1 5 cooler $end
$var reg 4 6 crs [3:0] $end
$upscope $end
$upscope $end
$enddefinitions $end
#0
$dumpvars
b10100 !
0"
0#
04
05
b0 6
0'
0&
0%
0$
0(
0)
03
02
01
00
1/
0.
1-
0,
0+
0*
$end
#10
1"
12
#20
1#
0"
13
02
#30
1"
12
#40
b101000 !
0"
0/
1.
0-
1,
02
#50
1"
12
15
b100 6
1)
1%
#60
b10100 !
0"
1/
0.
1-
0,
02
#70
1"
12
05
b0 6
0)
0%
#80
b1010 !
0"
10
0/
1.
0-
02
#90
1"
12
14
1(
#100
0#
0"
03
02
04
0(
#110
1"
12
#120
1#
0"
13
02
#130
1"
12
14
1(
#140
b101000 !
0"
00
1,
02
#150
1"
12
04
0(
#160
b101101 !
0"
11
1/
02
#170
1"
12
15
b100 6
1)
1%
#180
b110010 !
0"
01
10
0/
0.
1-
02
#190
1"
12
b110 6
1&
#200
0"
02
#210
1"
12
b1000 6
0&
0%
1$
#220
b10100 !
0"
00
1/
0,
02
#230
1"
12
b110 6
1&
1%
0$
#240
0"
02
#250
1"
12
b100 6
0&
#260
0"
02
#270
1"
12
05
b0 6
0)
0%
