Az4/AZ4/AZ4/stack.v
module stack(Clk, RstN, Data_In, Push, Pop, Data_Out, Full, Empty);
    parameter STACK_DEPTH = 8;
    parameter STACK_WIDTH = 4;

    input wire Clk, RstN, Push, Pop;
    input wire[STACK_WIDTH-1:0] Data_In;

    output Full, Empty;
    output reg [STACK_WIDTH-1:0] Data_Out;

    reg [STACK_WIDTH-1:0] stack [STACK_DEPTH-1:0];
    reg [STACK_DEPTH-1:0] count;
  
    assign Full = (count == STACK_DEPTH);
    assign Empty = (count == 0);
    integer i;
    always @(posedge Clk, negedge RstN) begin
      if(~RstN) begin
        count = 0;
        for(i = 0; i < STACK_DEPTH; i = i + 1)begin
          stack[i] = 0;
        end
      end
      else if(Pop && !Push && !Empty) begin
        Data_Out = stack[count - 1];
        count = count - 1;
      end
      else if(Push && !Pop && !Full) begin
        stack[count] = Data_In;
        $display("stack[%d] = %d", count, stack[count]);
        count = count + 1;
      end
    end
  endmodule

Az4/AZ4/AZ4/testbench.v
module testbench;
    parameter STACK_DEPTH = 8;
    parameter STACK_WIDTH = 4;
    reg Clk = 0, RstN = 0, Push = 0, Pop = 0;
    reg [STACK_WIDTH-1:0] Data_In;
    wire Full, Empty;
    wire [STACK_WIDTH-1:0] Data_Out;
    stack stackTest(Clk, RstN, Data_In, Push, Pop, Data_Out, Full, Empty);
    always #5 Clk = ~Clk;
    integer i;
    reg [STACK_WIDTH-1:0] temp = 8'b0;
    initial begin
        $dumpfile("wave.vcd");
        $dumpvars(0, testbench);
        RstN = 0;
        #5 RstN = 1;
        $display("Full = %d, Empty = %d", Full, Empty);
        for(i = 0; i < STACK_DEPTH; i = i + 1) begin
            Data_In = temp; Push = 1;
            #10 temp = temp + 1;
            $display("Full = %d, Empty = %d", Full, Empty);
        end 
        Push =0; Pop = 1;
        #10 $display("Data_Out = %d",Data_Out);
        Push =0; Pop = 1;
        #10 $display("Data_Out = %d",Data_Out);
        Push =0; Pop = 1;
        #10 $display("Data_Out = %d",Data_Out);
        Push =0; Pop = 1;
        #10 $display("Data_Out = %d",Data_Out);

        Data_In = 11; Push = 1; Pop = 0;
        #10 
        Data_In = 12; Push = 1; Pop = 0;
        #10
        Push =0; Pop = 1;
        #10 $display("Data_Out = %d",Data_Out);
        $display("Full = %d, Empty = %d", Full, Empty);
        $finish;
    end
endmodule

Az4/AZ4/AZ4/wave.vcd
$date
	Sat Jul 15 09:36:43 2023
$end
$version
	Icarus Verilog
$end
$timescale
	1s
$end
$scope module testbench $end
$var wire 1 ! Full $end
$var wire 1 " Empty $end
$var wire 4 # Data_Out [3:0] $end
$var reg 1 $ Clk $end
$var reg 4 % Data_In [3:0] $end
$var reg 1 & Pop $end
$var reg 1 ' Push $end
$var reg 1 ( RstN $end
$var reg 4 ) temp [3:0] $end
$var integer 32 * i [31:0] $end
$scope module stackTest $end
$var wire 1 $ Clk $end
$var wire 4 + Data_In [3:0] $end
$var wire 1 & Pop $end
$var wire 1 ' Push $end
$var wire 1 ( RstN $end
$var wire 1 ! Full $end
$var wire 1 " Empty $end
$var reg 4 , Data_Out [3:0] $end
$var reg 8 - count [7:0] $end
$var integer 32 . i [31:0] $end
$upscope $end
$upscope $end
$enddefinitions $end
#0
$dumpvars
b1000 .
b0 -
bx ,
bx +
bx *
b0 )
0(
0'
0&
bx %
0$
bx #
1"
0!
$end
#5
0"
b1 -
1'
b0 %
b0 +
b0 *
1(
1$
#10
0$
#15
b10 -
1$
b1 %
b1 +
b1 *
b1 )
#20
0$
#25
b11 -
1$
b10 %
b10 +
b10 *
b10 )
#30
0$
#35
b100 -
1$
b11 %
b11 +
b11 *
b11 )
#40
0$
#45
b101 -
1$
b100 %
b100 +
b100 *
b100 )
#50
0$
#55
b110 -
1$
b101 %
b101 +
b101 *
b101 )
#60
0$
#65
b111 -
1$
b110 %
b110 +
b110 *
b110 )
#70
0$
#75
1!
b1000 -
1$
b111 %
b111 +
b111 *
b111 )
#80
0$
#85
0!
b111 -
b111 #
b111 ,
1$
1&
0'
b1000 *
b1000 )
#90
0$
#95
b110 -
b110 #
b110 ,
1$
#100
0$
#105
b101 -
b101 #
b101 ,
1$
#110
0$
#115
b100 -
b100 #
b100 ,
1$
#120
0$
#125
b101 -
1$
0&
1'
b1011 %
b1011 +
#130
0$
#135
b110 -
1$
b1100 %
b1100 +
#140
0$
#145
b101 -
b1100 #
b1100 ,
1$
1&
0'
#150
0$
#155
b100 -
b1011 #
b1011 ,
1$
