Az3/Az3 - Final/1/bit_comparator.v
module bit_comparator (input wire a, b, Gin, Ein, Lin, output wire Gout, Eout, Lout);
    assign Eout = Ein && (a == b);
    assign Gout = a > b || ((a == b) && Gin);
    assign Lout = a < b || ((a == b) && Lin);
endmodule

Az3/Az3 - Final/1/comparator.v
module comparator(input [3:0]a, b, output G, E, L);
    wire [3:0]Gi;
    wire [3:0]Ei;
    wire [3:0]Li;
    
    bit_comparator bc0(a[0], b[0], 1'b0, 1'b1, 1'b0, Gi[0], Ei[0], Li[0]);
    bit_comparator bc1(a[1], b[1], Gi[0], Ei[0], Li[0], Gi[1], Ei[1], Li[1]);
    bit_comparator bc2(a[2], b[2], Gi[1], Ei[1], Li[1], Gi[2], Ei[2], Li[2]);
    bit_comparator bc3(a[3], b[3], Gi[2], Ei[2], Li[2], Gi[3], Ei[3], Li[3]);
    
    assign G = Gi[3];
    assign E = Ei[3];
    assign L = Li[3];
endmodule

Az3/Az3 - Final/1/TB.v
module TB;
    reg [3:0] a, b;
    wire G, E, L;

    comparator cmp(a, b, G, E, L);

    integer i, j;

    initial begin
        $dumpfile("waveform.vcd");
        $dumpvars(0, TB);
        a = 0; b = 0;
        for(i = 0; i < 16; i ++) begin
            for(j = 0; j < 16; j ++) begin
                #2 a = i; b = j;
            end
        end
        #2 $finish();
    end
endmodule

Az3/Az3 - Final/1/waveform.vcd
$date
	Sun Jul 16 23:23:54 2023
$end
$version
	Icarus Verilog
$end
$timescale
	1s
$end
$scope module TB $end
$var wire 1 ! L $end
$var wire 1 " G $end
$var wire 1 # E $end
$var reg 4 $ a [3:0] $end
$var reg 4 % b [3:0] $end
$var integer 32 & i [31:0] $end
$var integer 32 ' j [31:0] $end
$scope module cmp $end
$var wire 4 ( a [3:0] $end
$var wire 4 ) b [3:0] $end
$var wire 4 * Li [3:0] $end
$var wire 1 ! L $end
$var wire 4 + Gi [3:0] $end
$var wire 1 " G $end
$var wire 4 , Ei [3:0] $end
$var wire 1 # E $end
$scope module bc0 $end
$var wire 1 - Ein $end
$var wire 1 . Eout $end
$var wire 1 / Gin $end
$var wire 1 0 Gout $end
$var wire 1 1 Lin $end
$var wire 1 2 Lout $end
$var wire 1 3 a $end
$var wire 1 4 b $end
$upscope $end
$scope module bc1 $end
$var wire 1 5 Ein $end
$var wire 1 6 Eout $end
$var wire 1 7 Gin $end
$var wire 1 8 Gout $end
$var wire 1 9 Lin $end
$var wire 1 : Lout $end
$var wire 1 ; a $end
$var wire 1 < b $end
$upscope $end
$scope module bc2 $end
$var wire 1 = Ein $end
$var wire 1 > Eout $end
$var wire 1 ? Gin $end
$var wire 1 @ Gout $end
$var wire 1 A Lin $end
$var wire 1 B Lout $end
$var wire 1 C a $end
$var wire 1 D b $end
$upscope $end
$scope module bc3 $end
$var wire 1 E Ein $end
$var wire 1 F Eout $end
$var wire 1 G Gin $end
$var wire 1 H Gout $end
$var wire 1 I Lin $end
$var wire 1 J Lout $end
$var wire 1 K a $end
$var wire 1 L b $end
$upscope $end
$upscope $end
$upscope $end
$enddefinitions $end
#0
$dumpvars
0L
0K
0J
0I
0H
0G
1F
1E
0D
0C
0B
0A
0@
0?
1>
1=
0<
0;
0:
09
08
07
16
15
04
03
02
01
00
0/
1.
1-
b1111 ,
b0 +
b0 *
b0 )
b0 (
b0 '
b0 &
b0 %
b0 $
1#
0"
0!
$end
#2
b1 '
#4
1!
1J
0#
0F
1I
0E
1B
0>
0=
1A
06
1:
05
b0 ,
0.
19
b1111 *
12
14
b10 '
b1 %
b1 )
#6
15
b1 ,
1.
09
b1110 *
02
04
1<
b11 '
b10 %
b10 )
#8
05
b0 ,
0.
19
b1111 *
12
14
b100 '
b11 %
b11 )
#10
1=
16
15
b11 ,
1.
09
0A
02
b1100 *
0:
04
0<
1D
b101 '
b100 %
b100 )
#12
0=
1A
06
1:
05
b0 ,
0.
19
b1111 *
12
14
b110 '
b101 %
b101 )
#14
15
b1 ,
1.
09
b1110 *
02
04
1<
b111 '
b110 %
b110 )
#16
05
b0 ,
0.
19
b1111 *
12
14
b1000 '
b111 %
b111 )
#18
1E
1>
1=
16
15
b111 ,
1.
09
0A
0I
02
0:
b1000 *
0B
04
0<
0D
1L
b1001 '
b1000 %
b1000 )
#20
1I
0E
1B
0>
0=
1A
06
1:
05
b0 ,
0.
19
b1111 *
12
14
b1010 '
b1001 %
b1001 )
#22
15
b1 ,
1.
09
b1110 *
02
04
1<
b1011 '
b1010 %
b1010 )
#24
05
b0 ,
0.
19
b1111 *
12
14
b1100 '
b1011 %
b1011 )
#26
1=
16
15
b11 ,
1.
09
0A
02
b1100 *
0:
04
0<
1D
b1101 '
b1100 %
b1100 )
#28
0=
1A
06
1:
05
b0 ,
0.
19
b1111 *
12
14
b1110 '
b1101 %
b1101 )
#30
15
b1 ,
1.
09
b1110 *
02
04
1<
b1111 '
b1110 %
b1110 )
#32
05
b0 ,
0.
19
b1111 *
12
14
b1 &
b0 '
b1111 %
b1111 )
#34
1"
1H
1G
1@
1?
18
17
0A
0I
0!
09
b1111 +
10
0:
0B
0J
b0 *
02
04
0<
0D
0L
13
b1 '
b0 %
b0 )
b1 $
b1 (
#36
0"
0H
1#
1F
0G
1E
0@
1>
1=
0?
16
08
15
b1111 ,
1.
07
b0 +
00
14
b10 '
b1 %
b1 )
#38
1!
0#
1J
0F
0E
1I
0>
1B
05
0=
0.
17
b0 ,
06
1A
b1 +
10
b1110 *
1:
04
1<
b11 '
b10 %
b10 )
#40
15
b1 ,
1.
07
b0 +
00
14
b100 '
b11 %
b11 )
#42
1?
18
05
0=
0.
17
b0 ,
06
0A
b11 +
10
b1100 *
0:
04
0<
1D
b101 '
b100 %
b100 )
#44
1=
0?
16
08
15
b11 ,
1.
07
b0 +
00
14
b110 '
b101 %
b101 )
#46
05
0=
0.
17
b0 ,
06
1A
b1 +
10
b1110 *
1:
04
1<
b111 '
b110 %
b110 )
#48
15
b1 ,
1.
07
b0 +
00
14
b1000 '
b111 %
b111 )
#50
1G
1@
1?
0E
18
0>
05
0=
0.
17
b0 ,
06
0A
0I
b111 +
10
0:
b1000 *
0B
04
0<
0D
1L
b1001 '
b1000 %
b1000 )
#52
0G
1E
0@
1>
1=
0?
16
08
15
b111 ,
1.
07
b0 +
00
14
b1010 '
b1001 %
b1001 )
#54
0E
1I
0>
1B
05
0=
0.
17
b0 ,
06
1A
b1 +
10
b1110 *
1:
04
1<
b1011 '
b1010 %
b1010 )
#56
15
b1 ,
1.
07
b0 +
00
14
b1100 '
b1011 %
b1011 )
#58
1?
18
05
0=
0.
17
b0 ,
06
0A
b11 +
10
b1100 *
0:
04
0<
1D
b1101 '
b1100 %
b1100 )
#60
1=
0?
16
08
15
b11 ,
1.
07
b0 +
00
14
b1110 '
b1101 %
b1101 )
#62
05
0=
0.
17
b0 ,
06
1A
b1 +
10
b1110 *
1:
04
1<
b1111 '
b1110 %
b1110 )
#64
15
b1 ,
1.
07
b0 +
00
14
b10 &
b0 '
b1111 %
b1111 )
#66
1"
1H
1G
1@
1?
0I
0!
0A
b1110 +
18
0B
0J
b0 *
0:
04
0<
0D
0L
03
1;
b1 '
b0 %
b0 )
b10 $
b10 (
#68
05
b0 ,
0.
19
b1 *
12
14
b10 '
b1 %
b1 )
#70
0!
1#
0J
1F
0"
1E
0I
0H
1>
0B
1=
0G
16
0A
0@
15
0:
b1111 ,
1.
09
0?
b0 *
02
b0 +
08
04
1<
b11 '
b10 %
b10 )
#72
1!
1J
0#
0F
1I
0E
1B
0>
0=
1A
06
1:
05
b0 ,
0.
19
b1111 *
12
14
b100 '
b11 %
b11 )
#74
0A
15
0:
b1 ,
1.
09
1?
b1100 *
02
b10 +
18
04
0<
1D
b101 '
b100 %
b100 )
#76
05
b0 ,
0.
19
b1101 *
12
14
b110 '
b101 %
b101 )
#78
1=
16
0A
15
0:
b11 ,
1.
09
0?
b1100 *
02
b0 +
08
04
1<
b111 '
b110 %
b110 )
#80
0=
1A
06
1:
05
b0 ,
0.
19
b1111 *
12
14
b1000 '
b111 %
b111 )
#82
1G
0A
1@
15
0:
b1 ,
1.
09
1?
0I
02
b110 +
18
b1000 *
0B
04
0<
0D
1L
b1001 '
b1000 %
b1000 )
#84
05
b0 ,
0.
19
b1001 *
12
14
b1010 '
b1001 %
b1001 )
#86
1E
0I
1>
0B
1=
0G
16
0A
0@
15
0:
b111 ,
1.
09
0?
b1000 *
02
b0 +
08
04
1<
b1011 '
b1010 %
b1010 )
#88
1I
0E
1B
0>
0=
1A
06
1:
05
b0 ,
0.
19
b1111 *
12
14
b1100 '
b1011 %
b1011 )
#90
0A
15
0:
b1 ,
1.
09
1?
b1100 *
02
b10 +
18
04
0<
1D
b1101 '
b1100 %
b1100 )
#92
05
b0 ,
0.
19
b1101 *
12
14
b1110 '
b1101 %
b1101 )
#94
1=
16
0A
15
0:
b11 ,
1.
09
0?
b1100 *
02
b0 +
08
04
1<
b1111 '
b1110 %
b1110 )
#96
0=
1A
06
1:
05
b0 ,
0.
19
b1111 *
12
14
b11 &
b0 '
b1111 %
b1111 )
#98
1"
1H
1G
0A
1@
0:
17
1?
0I
0!
09
10
b1111 +
18
0B
0J
b0 *
02
04
0<
0D
0L
13
b1 '
b0 %
b0 )
b11 $
b11 (
#100
15
b1 ,
1.
07
b1110 +
00
14
b10 '
b1 %
b1 )
#102
1"
0#
1H
0F
0E
1G
0>
1@
05
0=
0.
17
b0 ,
06
1?
10
b1111 +
18
04
1<
b11 '
b10 %
b10 )
#104
0"
0H
1#
1F
0G
1E
0@
1>
1=
0?
16
08
15
b1111 ,
1.
07
b0 +
00
14
b100 '
b11 %
b11 )
#106
0#
1!
0F
1J
05
0=
0E
0.
17
06
1?
b0 ,
0>
1I
10
b11 +
18
b1100 *
1B
04
0<
1D
b101 '
b100 %
b100 )
#108
15
b1 ,
1.
07
b10 +
00
14
b110 '
b101 %
b101 )
#110
05
0=
0.
17
b0 ,
06
1?
10
b11 +
18
04
1<
b111 '
b110 %
b110 )
#112
1=
0?
16
08
15
b11 ,
1.
07
b0 +
00
14
b1000 '
b111 %
b111 )
#114
1G
1@
05
0=
0E
0.
17
06
1?
b0 ,
0>
0I
10
b111 +
18
b1000 *
0B
04
0<
0D
1L
b1001 '
b1000 %
b1000 )
#116
15
b1 ,
1.
07
b110 +
00
14
b1010 '
b1001 %
b1001 )
#118
0E
1G
0>
1@
05
0=
0.
17
b0 ,
06
1?
10
b111 +
18
04
1<
b1011 '
b1010 %
b1010 )
#120
0G
1E
0@
1>
1=
0?
16
08
15
b111 ,
1.
07
b0 +
00
14
b1100 '
b1011 %
b1011 )
#122
05
0=
0E
0.
17
06
1?
b0 ,
0>
1I
10
b11 +
18
b1100 *
1B
04
0<
1D
b1101 '
b1100 %
b1100 )
#124
15
b1 ,
1.
07
b10 +
00
14
b1110 '
b1101 %
b1101 )
#126
05
0=
0.
17
b0 ,
06
1?
10
b11 +
18
04
1<
b1111 '
b1110 %
b1110 )
#128
1=
0?
16
08
15
b11 ,
1.
07
b0 +
00
14
b100 &
b0 '
b1111 %
b1111 )
#130
1"
1H
1G
0!
0I
b1100 +
1@
0J
b0 *
0B
04
0<
0D
0L
03
0;
1C
b1 '
b0 %
b0 )
b100 $
b100 (
#132
0=
1A
06
1:
05
b0 ,
0.
19
b11 *
12
14
b10 '
b1 %
b1 )
#134
15
b1 ,
1.
09
b10 *
02
04
1<
b11 '
b10 %
b10 )
#136
05
b0 ,
0.
19
b11 *
12
14
b100 '
b11 %
b11 )
#138
1#
1F
1E
0!
1>
0J
1=
0"
16
0I
0H
15
0B
b1111 ,
1.
09
0A
0G
02
b0 *
0:
b0 +
0@
04
0<
1D
b101 '
b100 %
b100 )
#140
1!
1J
0#
0F
1I
0E
1B
0>
0=
1A
06
1:
05
b0 ,
0.
19
b1111 *
12
14
b110 '
b101 %
b101 )
#142
15
b1 ,
1.
09
b1110 *
02
04
1<
b111 '
b110 %
b110 )
#144
05
b0 ,
0.
19
b1111 *
12
14
b1000 '
b111 %
b111 )
#146
1=
16
0I
15
0B
b11 ,
1.
09
0A
1G
02
b1000 *
0:
b100 +
1@
04
0<
0D
1L
b1001 '
b1000 %
b1000 )
#148
0=
1A
06
1:
05
b0 ,
0.
19
b1011 *
12
14
b1010 '
b1001 %
b1001 )
#150
15
b1 ,
1.
09
b1010 *
02
04
1<
b1011 '
b1010 %
b1010 )
#152
05
b0 ,
0.
19
b1011 *
12
14
b1100 '
b1011 %
b1011 )
#154
1E
1>
1=
16
0I
15
0B
b111 ,
1.
09
0A
0G
02
b1000 *
0:
b0 +
0@
04
0<
1D
b1101 '
b1100 %
b1100 )
#156
1I
0E
1B
0>
0=
1A
06
1:
05
b0 ,
0.
19
b1111 *
12
14
b1110 '
b1101 %
b1101 )
#158
15
b1 ,
1.
09
b1110 *
02
04
1<
b1111 '
b1110 %
b1110 )
#160
05
b0 ,
0.
19
b1111 *
12
14
b101 &
b0 '
b1111 %
b1111 )
#162
1?
1"
18
0I
1H
0B
17
0A
1G
0!
09
10
0:
b1111 +
1@
0J
b0 *
02
04
0<
0D
0L
13
b1 '
b0 %
b0 )
b101 $
b101 (
#164
1=
0?
16
08
15
b11 ,
1.
07
b1100 +
00
14
b10 '
b1 %
b1 )
#166
05
0=
0.
17
b0 ,
06
1A
b1101 +
10
b10 *
1:
04
1<
b11 '
b10 %
b10 )
#168
15
b1 ,
1.
07
b1100 +
00
14
b100 '
b11 %
b11 )
#170
0#
0!
0F
0J
1?
0E
1"
18
0>
0I
1H
05
0=
0B
0.
17
b0 ,
06
0A
1G
10
b0 *
0:
b1111 +
1@
04
0<
1D
b101 '
b100 %
b100 )
#172
0"
0H
1#
1F
0G
1E
0@
1>
1=
0?
16
08
15
b1111 ,
1.
07
b0 +
00
14
b110 '
b101 %
b101 )
#174
1!
0#
1J
0F
0E
1I
0>
1B
05
0=
0.
17
b0 ,
06
1A
b1 +
10
b1110 *
1:
04
1<
b111 '
b110 %
b110 )
#176
15
b1 ,
1.
07
b0 +
00
14
b1000 '
b111 %
b111 )
#178
1?
18
0I
05
0=
0B
0.
17
b0 ,
06
0A
1G
10
b1000 *
0:
b111 +
1@
04
0<
0D
1L
b1001 '
b1000 %
b1000 )
#180
1=
0?
16
08
15
b11 ,
1.
07
b100 +
00
14
b1010 '
b1001 %
b1001 )
#182
05
0=
0.
17
b0 ,
06
1A
b101 +
10
b1010 *
1:
04
1<
b1011 '
b1010 %
b1010 )
#184
15
b1 ,
1.
07
b100 +
00
14
b1100 '
b1011 %
b1011 )
#186
1?
0E
18
0>
0I
05
0=
0B
0.
17
b0 ,
06
0A
1G
10
b1000 *
0:
b111 +
1@
04
0<
1D
b1101 '
b1100 %
b1100 )
#188
0G
1E
0@
1>
1=
0?
16
08
15
b111 ,
1.
07
b0 +
00
14
b1110 '
b1101 %
b1101 )
#190
0E
1I
0>
1B
05
0=
0.
17
b0 ,
06
1A
b1 +
10
b1110 *
1:
04
1<
b1111 '
b1110 %
b1110 )
#192
15
b1 ,
1.
07
b0 +
00
14
b110 &
b0 '
b1111 %
b1111 )
#194
1"
0I
1H
0B
1?
1G
0!
0A
18
b1110 +
1@
0J
b0 *
0:
04
0<
0D
0L
03
1;
b1 '
b0 %
b0 )
b110 $
b110 (
#196
05
b0 ,
0.
19
b1 *
12
14
b10 '
b1 %
b1 )
#198
1=
16
0A
15
0:
b11 ,
1.
09
0?
b0 *
02
b1100 +
08
04
1<
b11 '
b10 %
b10 )
#200
0=
1A
06
1:
05
b0 ,
0.
19
b11 *
12
14
b100 '
b11 %
b11 )
#202
0!
0J
1"
0A
0I
1H
15
0:
0B
b1 ,
1.
09
1?
1G
b0 *
02
18
b1110 +
1@
04
0<
1D
b101 '
b100 %
b100 )
#204
05
b0 ,
0.
19
b1 *
12
14
b110 '
b101 %
b101 )
#206
0!
1#
0J
1F
0"
1E
0I
0H
1>
0B
1=
0G
16
0A
0@
15
0:
b1111 ,
1.
09
0?
b0 *
02
b0 +
08
04
1<
b111 '
b110 %
b110 )
#208
1!
1J
0#
0F
1I
0E
1B
0>
0=
1A
06
1:
05
b0 ,
0.
19
b1111 *
12
14
b1000 '
b111 %
b111 )
#210
0A
0I
15
0:
0B
b1 ,
1.
09
1?
1G
b1000 *
02
18
b110 +
1@
04
0<
0D
1L
b1001 '
b1000 %
b1000 )
#212
05
b0 ,
0.
19
b1001 *
12
14
b1010 '
b1001 %
b1001 )
#214
1=
16
0A
15
0:
b11 ,
1.
09
0?
b1000 *
02
b100 +
08
04
1<
b1011 '
b1010 %
b1010 )
#216
0=
1A
06
1:
05
b0 ,
0.
19
b1011 *
12
14
b1100 '
b1011 %
b1011 )
#218
0A
0I
15
0:
0B
b1 ,
1.
09
1?
1G
b1000 *
02
18
b110 +
1@
04
0<
1D
b1101 '
b1100 %
b1100 )
#220
05
b0 ,
0.
19
b1001 *
12
14
b1110 '
b1101 %
b1101 )
#222
1E
0I
1>
0B
1=
0G
16
0A
0@
15
0:
b111 ,
1.
09
0?
b1000 *
02
b0 +
08
04
1<
b1111 '
b1110 %
b1110 )
#224
1I
0E
1B
0>
0=
1A
06
1:
05
b0 ,
0.
19
b1111 *
12
14
b111 &
b0 '
b1111 %
b1111 )
#226
1"
0A
0I
1H
0:
0B
17
1?
1G
0!
09
10
18
b1111 +
1@
0J
b0 *
02
04
0<
0D
0L
13
b1 '
b0 %
b0 )
b111 $
b111 (
#228
15
b1 ,
1.
07
b1110 +
00
14
b10 '
b1 %
b1 )
#230
05
0=
0.
17
b0 ,
06
1?
10
b1111 +
18
04
1<
b11 '
b10 %
b10 )
#232
1=
0?
16
08
15
b11 ,
1.
07
b1100 +
00
14
b100 '
b11 %
b11 )
#234
0#
1"
0F
1H
05
0=
0E
0.
17
06
1?
b0 ,
0>
1G
10
18
b1111 +
1@
04
0<
1D
b101 '
b100 %
b100 )
#236
15
b1 ,
1.
07
b1110 +
00
14
b110 '
b101 %
b101 )
#238
1"
0#
1H
0F
0E
1G
0>
1@
05
0=
0.
17
b0 ,
06
1?
10
b1111 +
18
04
1<
b111 '
b110 %
b110 )
#240
0"
0H
1#
1F
0G
1E
0@
1>
1=
0?
16
08
15
b1111 ,
1.
07
b0 +
00
14
b1000 '
b111 %
b111 )
#242
05
0=
0E
0#
0.
17
06
1?
0>
1G
b0 ,
0F
1!
10
18
b111 +
1@
b1000 *
1J
04
0<
0D
1L
b1001 '
b1000 %
b1000 )
#244
15
b1 ,
1.
07
b110 +
00
14
b1010 '
b1001 %
b1001 )
#246
05
0=
0.
17
b0 ,
06
1?
10
b111 +
18
04
1<
b1011 '
b1010 %
b1010 )
#248
1=
0?
16
08
15
b11 ,
1.
07
b100 +
00
14
b1100 '
b1011 %
b1011 )
#250
05
0=
0E
0.
17
06
1?
b0 ,
0>
1G
10
18
b111 +
1@
04
0<
1D
b1101 '
b1100 %
b1100 )
#252
15
b1 ,
1.
07
b110 +
00
14
b1110 '
b1101 %
b1101 )
#254
0E
1G
0>
1@
05
0=
0.
17
b0 ,
06
1?
10
b111 +
18
04
1<
b1111 '
b1110 %
b1110 )
#256
0G
1E
0@
1>
1=
0?
16
08
15
b111 ,
1.
07
b0 +
00
14
b1000 &
b0 '
b1111 %
b1111 )
#258
1"
0!
b1000 +
1H
b0 *
0J
04
0<
0D
0L
03
0;
0C
1K
b1 '
b0 %
b0 )
b1000 $
b1000 (
#260
1I
0E
1B
0>
0=
1A
06
1:
05
b0 ,
0.
19
b111 *
12
14
b10 '
b1 %
b1 )
#262
15
b1 ,
1.
09
b110 *
02
04
1<
b11 '
b10 %
b10 )
#264
05
b0 ,
0.
19
b111 *
12
14
b100 '
b11 %
b11 )
#266
1=
16
15
b11 ,
1.
09
0A
02
b100 *
0:
04
0<
1D
b101 '
b100 %
b100 )
#268
0=
1A
06
1:
05
b0 ,
0.
19
b111 *
12
14
b110 '
b101 %
b101 )
#270
15
b1 ,
1.
09
b110 *
02
04
1<
b111 '
b110 %
b110 )
#272
05
b0 ,
0.
19
b111 *
12
14
b1000 '
b111 %
b111 )
#274
1#
1F
1E
1>
1=
16
0!
15
0J
b1111 ,
1.
09
0A
0I
0"
02
0:
b0 *
0B
b0 +
0H
04
0<
0D
1L
b1001 '
b1000 %
b1000 )
#276
1!
1J
0#
0F
1I
0E
1B
0>
0=
1A
06
1:
05
b0 ,
0.
19
b1111 *
12
14
b1010 '
b1001 %
b1001 )
#278
15
b1 ,
1.
09
b1110 *
02
04
1<
b1011 '
b1010 %
b1010 )
#280
05
b0 ,
0.
19
b1111 *
12
14
b1100 '
b1011 %
b1011 )
#282
1=
16
15
b11 ,
1.
09
0A
02
b1100 *
0:
04
0<
1D
b1101 '
b1100 %
b1100 )
#284
0=
1A
06
1:
05
b0 ,
0.
19
b1111 *
12
14
b1110 '
b1101 %
b1101 )
#286
15
b1 ,
1.
09
b1110 *
02
04
1<
b1111 '
b1110 %
b1110 )
#288
05
b0 ,
0.
19
b1111 *
12
14
b1001 &
b0 '
b1111 %
b1111 )
#290
1G
1@
1?
18
0!
0J
17
0A
0I
1"
09
10
0:
0B
b1111 +
1H
b0 *
02
04
0<
0D
0L
13
b1 '
b0 %
b0 )
b1001 $
b1001 (
#292
0G
1E
0@
1>
1=
0?
16
08
15
b111 ,
1.
07
b1000 +
00
14
b10 '
b1 %
b1 )
#294
0E
1I
0>
1B
05
0=
0.
17
b0 ,
06
1A
b1001 +
10
b110 *
1:
04
1<
b11 '
b10 %
b10 )
#296
15
b1 ,
1.
07
b1000 +
00
14
b100 '
b11 %
b11 )
#298
1?
18
05
0=
0.
17
b0 ,
06
0A
b1011 +
10
b100 *
0:
04
0<
1D
b101 '
b100 %
b100 )
#300
1=
0?
16
08
15
b11 ,
1.
07
b1000 +
00
14
b110 '
b101 %
b101 )
#302
05
0=
0.
17
b0 ,
06
1A
b1001 +
10
b110 *
1:
04
1<
b111 '
b110 %
b110 )
#304
15
b1 ,
1.
07
b1000 +
00
14
b1000 '
b111 %
b111 )
#306
1G
1@
0#
0F
1?
0E
18
0>
0!
05
0=
0J
0.
17
b0 ,
06
0A
0I
1"
10
0:
b0 *
0B
b1111 +
1H
04
0<
0D
1L
b1001 '
b1000 %
b1000 )
#308
0"
0H
1#
1F
0G
1E
0@
1>
1=
0?
16
08
15
b1111 ,
1.
07
b0 +
00
14
b1010 '
b1001 %
b1001 )
#310
1!
0#
1J
0F
0E
1I
0>
1B
05
0=
0.
17
b0 ,
06
1A
b1 +
10
b1110 *
1:
04
1<
b1011 '
b1010 %
b1010 )
#312
15
b1 ,
1.
07
b0 +
00
14
b1100 '
b1011 %
b1011 )
#314
1?
18
05
0=
0.
17
b0 ,
06
0A
b11 +
10
b1100 *
0:
04
0<
1D
b1101 '
b1100 %
b1100 )
#316
1=
0?
16
08
15
b11 ,
1.
07
b0 +
00
14
b1110 '
b1101 %
b1101 )
#318
05
0=
0.
17
b0 ,
06
1A
b1 +
10
b1110 *
1:
04
1<
b1111 '
b1110 %
b1110 )
#320
15
b1 ,
1.
07
b0 +
00
14
b1010 &
b0 '
b1111 %
b1111 )
#322
1G
1@
0!
0J
1?
0I
1"
0A
18
0B
b1110 +
1H
b0 *
0:
04
0<
0D
0L
03
1;
b1 '
b0 %
b0 )
b1010 $
b1010 (
#324
05
b0 ,
0.
19
b1 *
12
14
b10 '
b1 %
b1 )
#326
1E
0I
1>
0B
1=
0G
16
0A
0@
15
0:
b111 ,
1.
09
0?
b0 *
02
b1000 +
08
04
1<
b11 '
b10 %
b10 )
#328
1I
0E
1B
0>
0=
1A
06
1:
05
b0 ,
0.
19
b111 *
12
14
b100 '
b11 %
b11 )
#330
0A
15
0:
b1 ,
1.
09
1?
b100 *
02
b1010 +
18
04
0<
1D
b101 '
b100 %
b100 )
#332
05
b0 ,
0.
19
b101 *
12
14
b110 '
b101 %
b101 )
#334
1=
16
0A
15
0:
b11 ,
1.
09
0?
b100 *
02
b1000 +
08
04
1<
b111 '
b110 %
b110 )
#336
0=
1A
06
1:
05
b0 ,
0.
19
b111 *
12
14
b1000 '
b111 %
b111 )
#338
1G
0A
1@
0!
15
0:
0J
b1 ,
1.
09
1?
0I
1"
02
18
b0 *
0B
b1110 +
1H
04
0<
0D
1L
b1001 '
b1000 %
b1000 )
#340
05
b0 ,
0.
19
b1 *
12
14
b1010 '
b1001 %
b1001 )
#342
0!
1#
0J
1F
0"
1E
0I
0H
1>
0B
1=
0G
16
0A
0@
15
0:
b1111 ,
1.
09
0?
b0 *
02
b0 +
08
04
1<
b1011 '
b1010 %
b1010 )
#344
1!
1J
0#
0F
1I
0E
1B
0>
0=
1A
06
1:
05
b0 ,
0.
19
b1111 *
12
14
b1100 '
b1011 %
b1011 )
#346
0A
15
0:
b1 ,
1.
09
1?
b1100 *
02
b10 +
18
04
0<
1D
b1101 '
b1100 %
b1100 )
#348
05
b0 ,
0.
19
b1101 *
12
14
b1110 '
b1101 %
b1101 )
#350
1=
16
0A
15
0:
b11 ,
1.
09
0?
b1100 *
02
b0 +
08
04
1<
b1111 '
b1110 %
b1110 )
#352
0=
1A
06
1:
05
b0 ,
0.
19
b1111 *
12
14
b1011 &
b0 '
b1111 %
b1111 )
#354
1G
0A
1@
0!
0:
0J
17
1?
0I
1"
09
10
18
0B
b1111 +
1H
b0 *
02
04
0<
0D
0L
13
b1 '
b0 %
b0 )
b1011 $
b1011 (
#356
15
b1 ,
1.
07
b1110 +
00
14
b10 '
b1 %
b1 )
#358
0E
1G
0>
1@
05
0=
0.
17
b0 ,
06
1?
10
b1111 +
18
04
1<
b11 '
b10 %
b10 )
#360
0G
1E
0@
1>
1=
0?
16
08
15
b111 ,
1.
07
b1000 +
00
14
b100 '
b11 %
b11 )
#362
05
0=
0E
0.
17
06
1?
b0 ,
0>
1I
10
b1011 +
18
b100 *
1B
04
0<
1D
b101 '
b100 %
b100 )
#364
15
b1 ,
1.
07
b1010 +
00
14
b110 '
b101 %
b101 )
#366
05
0=
0.
17
b0 ,
06
1?
10
b1011 +
18
04
1<
b111 '
b110 %
b110 )
#368
1=
0?
16
08
15
b11 ,
1.
07
b1000 +
00
14
b1000 '
b111 %
b111 )
#370
1G
0#
1@
0F
0!
05
0=
0E
0J
0.
17
06
1?
b0 ,
0>
0I
1"
10
18
b0 *
0B
b1111 +
1H
04
0<
0D
1L
b1001 '
b1000 %
b1000 )
#372
15
b1 ,
1.
07
b1110 +
00
14
b1010 '
b1001 %
b1001 )
#374
1"
0#
1H
0F
0E
1G
0>
1@
05
0=
0.
17
b0 ,
06
1?
10
b1111 +
18
04
1<
b1011 '
b1010 %
b1010 )
#376
0"
0H
1#
1F
0G
1E
0@
1>
1=
0?
16
08
15
b1111 ,
1.
07
b0 +
00
14
b1100 '
b1011 %
b1011 )
#378
0#
1!
0F
1J
05
0=
0E
0.
17
06
1?
b0 ,
0>
1I
10
b11 +
18
b1100 *
1B
04
0<
1D
b1101 '
b1100 %
b1100 )
#380
15
b1 ,
1.
07
b10 +
00
14
b1110 '
b1101 %
b1101 )
#382
05
0=
0.
17
b0 ,
06
1?
10
b11 +
18
04
1<
b1111 '
b1110 %
b1110 )
#384
1=
0?
16
08
15
b11 ,
1.
07
b0 +
00
14
b1100 &
b0 '
b1111 %
b1111 )
#386
0!
0J
1G
1"
0I
1@
b1100 +
1H
b0 *
0B
04
0<
0D
0L
03
0;
1C
b1 '
b0 %
b0 )
b1100 $
b1100 (
#388
0=
1A
06
1:
05
b0 ,
0.
19
b11 *
12
14
b10 '
b1 %
b1 )
#390
15
b1 ,
1.
09
b10 *
02
04
1<
b11 '
b10 %
b10 )
#392
05
b0 ,
0.
19
b11 *
12
14
b100 '
b11 %
b11 )
#394
1E
1>
1=
16
0I
15
0B
b111 ,
1.
09
0A
0G
02
b0 *
0:
b1000 +
0@
04
0<
1D
b101 '
b100 %
b100 )
#396
1I
0E
1B
0>
0=
1A
06
1:
05
b0 ,
0.
19
b111 *
12
14
b110 '
b101 %
b101 )
#398
15
b1 ,
1.
09
b110 *
02
04
1<
b111 '
b110 %
b110 )
#400
05
b0 ,
0.
19
b111 *
12
14
b1000 '
b111 %
b111 )
#402
1=
16
0I
0!
15
0B
0J
b11 ,
1.
09
0A
1G
1"
02
b0 *
0:
1@
b1100 +
1H
04
0<
0D
1L
b1001 '
b1000 %
b1000 )
#404
0=
1A
06
1:
05
b0 ,
0.
19
b11 *
12
14
b1010 '
b1001 %
b1001 )
#406
15
b1 ,
1.
09
b10 *
02
04
1<
b1011 '
b1010 %
b1010 )
#408
05
b0 ,
0.
19
b11 *
12
14
b1100 '
b1011 %
b1011 )
#410
1#
1F
1E
0!
1>
0J
1=
0"
16
0I
0H
15
0B
b1111 ,
1.
09
0A
0G
02
b0 *
0:
b0 +
0@
04
0<
1D
b1101 '
b1100 %
b1100 )
#412
1!
1J
0#
0F
1I
0E
1B
0>
0=
1A
06
1:
05
b0 ,
0.
19
b1111 *
12
14
b1110 '
b1101 %
b1101 )
#414
15
b1 ,
1.
09
b1110 *
02
04
1<
b1111 '
b1110 %
b1110 )
#416
05
b0 ,
0.
19
b1111 *
12
14
b1101 &
b0 '
b1111 %
b1111 )
#418
1?
18
0I
0!
0B
0J
17
0A
1G
1"
09
10
0:
1@
b1111 +
1H
b0 *
02
04
0<
0D
0L
13
b1 '
b0 %
b0 )
b1101 $
b1101 (
#420
1=
0?
16
08
15
b11 ,
1.
07
b1100 +
00
14
b10 '
b1 %
b1 )
#422
05
0=
0.
17
b0 ,
06
1A
b1101 +
10
b10 *
1:
04
1<
b11 '
b10 %
b10 )
#424
15
b1 ,
1.
07
b1100 +
00
14
b100 '
b11 %
b11 )
