Az3/Az3 - Final/2/comparator.v
module comparator(input a, b, clk, reset, output G, E, L);
    wire Gn, En, Ln; // inverse of G E L
    wire Gin, Ein, Lin; // computed G E L based on previous state;

    assign Gin = (~reset) && (G || (E && (a > b)));
    assign Ein = reset || (E && (a == b));
    assign Lin = (~reset) && (L || (E && (a < b)));

    // 1st layer Latches
    assign G1 = ~(G1n && ~(Gin && ~clk));
    assign G1n = ~(G1 && ~(~Gin && ~clk));
    assign E1 = ~(E1n && ~(Ein && ~clk));
    assign E1n = ~(E1 && ~(~Ein && ~clk));
    assign L1 = ~(L1n && ~(Lin && ~clk));
    assign L1n = ~(L1 && ~(~Lin && ~clk));
    // 2nd layer Latches
    assign G2 = ~(G2n && ~(G1 && clk));
    assign G2n = ~(G2 && ~(~G1 && clk));
    assign E2 = ~(E2n && ~(E1 && clk));
    assign E2n = ~(E2 && ~(~E1 && clk));
    assign L2 = ~(L2n && ~(L1 && clk));
    assign L2n = ~(L2 && ~(~L1 && clk));
    
    assign G = G2;
    assign E = E2;
    assign L = L2;
endmodule

Az3/Az3 - Final/2/TB.v
module TB;
    reg a, b, clk = 1, reset;
    wire G, E, L;

    comparator cmp(a, b, clk, reset, G, E, L);

    always #2 clk = ~clk;

    initial begin
        $dumpfile("waveform.vcd");
        $dumpvars(0, TB);
        reset = 1; a = 0; b = 0;
        #4 reset = 0; a = 0; b = 0;
        #4 a = 1; b = 1;
        #4 a = 0; b = 1;
        #4 a = 1; b = 0;
        #4 a = 1; b = 1;
        #4 reset = 1;
        #4 reset = 0; a = 0; b = 0;
        #4 a = 1; b = 1;
        #4 a = 1; b = 0;
        #4 a = 0; b = 1;
        #4 a = 0; b = 0;
        #4 $finish();
    end
endmodule

Az3/Az3 - Final/2/waveform.vcd
$date
	Sun Jul 16 21:29:36 2023
$end
$version
	Icarus Verilog
$end
$timescale
	1s
$end
$scope module TB $end
$var wire 1 ! L $end
$var wire 1 " G $end
$var wire 1 # E $end
$var reg 1 $ a $end
$var reg 1 % b $end
$var reg 1 & clk $end
$var reg 1 ' reset $end
$scope module cmp $end
$var wire 1 # E $end
$var wire 1 ( Ein $end
$var wire 1 ) En $end
$var wire 1 " G $end
$var wire 1 * Gin $end
$var wire 1 + Gn $end
$var wire 1 ! L $end
$var wire 1 , Lin $end
$var wire 1 - Ln $end
$var wire 1 $ a $end
$var wire 1 % b $end
$var wire 1 & clk $end
$var wire 1 ' reset $end
$upscope $end
$upscope $end
$enddefinitions $end
#0
$dumpvars
1-
0,
1+
0*
0)
1(
1'
1&
0%
0$
1#
0"
0!
$end
#2
0&
#4
1&
0'
#6
0&
#8
1&
1%
1$
#10
0&
#12
0#
0-
1)
1!
0(
1,
1&
0$
#14
0&
#16
1&
0%
1$
#18
0&
#20
1&
1%
#22
0&
#24
0!
1-
0)
1#
0,
1(
1&
1'
#26
0&
#28
1&
0%
0$
0'
#30
0&
#32
1&
1%
1$
#34
0&
#36
0#
0+
1)
1"
0(
1*
1&
0%
#38
0&
#40
1&
1%
0$
#42
0&
#44
1&
0%
