Az5/Code/DataPath.v
module DataPath (
    input wire [3:0] multiplier, multiplicand,
    input rstn, clk,
    input [2:0] shift,
    input op,
    input finish,
    output wire [7:0] result,
    output reg [2:0] counter
);

reg signed [3:0] A, B, C;

assign result = {C, B};

always @(posedge clk or negedge rstn) begin
    if(!rstn) begin
        A = multiplicand;
        B = multiplier;
        C = 0;
        counter = 3'b100;
    end
    else begin
        #1 
        if(!finish) begin
            if(shift == 1) {C, B} = {C[3], C, B[3:1]};
            else if(shift == 2) {C, B} = {C[3], C[3], C, B[3:2]};
            else if(shift == 3) {C, B} = {C[3], C[3], C[3], C, B[3]};
            else if(shift == 4) {C, B} = {C[3], C[3], C[3], C[3], C};
            counter = counter - shift;
            $display("pre %b ? %b", result, A);
            if(counter > 0 || op) begin
                if(op) C = C + A;
                else C = C - A;
            end
            $display("post %b", result);
        end
    end
end
    
endmodule

Az5/Code/ControlUnit.v
module ControlUnit (
    input wire [2:0]counter,
    input [7:0] result,
    input rstn, clk,
    output reg [2:0] shift,
    output reg op,
    output reg finish
);

always @(posedge clk or negedge rstn) begin
    if(!rstn) begin
        finish = 0;
        shift = 0;
        op = 1;
    end
    else begin
        if(!finish) begin
            if(counter == 0) finish = 1;
            if(result[0] == op || counter == 0) shift = 0;
            else if(result[1] == op || counter == 1) shift = 1;
            else if(result[2] == op || counter == 2) shift = 2;
            else if(result[3] == op || counter == 3) shift = 3;
            else shift = 4;
            op = ~op;
        end
    end
end


endmodule

Az5/Code/Multiply.v
module Multiply (
    input wire[3:0] multiplier, multiplicand, 
    input rstn, clk,
    output [7:0]result,
    output finish
);

wire[2:0] shift, counter;

ControlUnit CU(counter, result, rstn, clk, shift, op, finish);
DataPath DP(multiplier, multiplicand, rstn, clk, shift, op, finish, result, counter);

endmodule

Az5/Code/TB.v
module TB;
    reg [3:0] A, B;
    reg rstn = 1, clk = 1;
    wire [7:0] res;
    wire finish;

    Multiply mul(A, B, rstn, clk, res, finish);

    always #5 clk = ~clk;

    initial begin
        $dumpfile("waveform.vcd");
        $dumpvars(0, TB);
        rstn = 0;
        A = 6; B = 7;
        #10
        rstn = 1;
        #50
        rstn = 0;
        A = 3; B = 3;
        #10
        rstn = 1;
        #50
        rstn = 0;
        A = 8; B = 5;
        #10
        rstn = 1;
        #50
        $finish();
    end

endmodule

Az5/Code/waveform.vcd
$date
	Mon Aug 07 12:28:43 2023
$end
$version
	Icarus Verilog
$end
$timescale
	1s
$end
$scope module TB $end
$var wire 8 ! res [7:0] $end
$var wire 1 " finish $end
$var reg 4 # A [3:0] $end
$var reg 4 $ B [3:0] $end
$var reg 1 % clk $end
$var reg 1 & rstn $end
$scope module mul $end
$var wire 1 % clk $end
$var wire 4 ' multiplicand [3:0] $end
$var wire 4 ( multiplier [3:0] $end
$var wire 1 & rstn $end
$var wire 3 ) shift [2:0] $end
$var wire 8 * result [7:0] $end
$var wire 1 + op $end
$var wire 1 " finish $end
$var wire 3 , counter [2:0] $end
$scope module CU $end
$var wire 1 % clk $end
$var wire 1 & rstn $end
$var wire 8 - result [7:0] $end
$var wire 3 . counter [2:0] $end
$var reg 1 " finish $end
$var reg 1 + op $end
$var reg 3 / shift [2:0] $end
$upscope $end
$scope module DP $end
$var wire 1 % clk $end
$var wire 1 " finish $end
$var wire 4 0 multiplicand [3:0] $end
$var wire 4 1 multiplier [3:0] $end
$var wire 1 + op $end
$var wire 1 & rstn $end
$var wire 3 2 shift [2:0] $end
$var wire 8 3 result [7:0] $end
$var reg 4 4 A [3:0] $end
$var reg 4 5 B [3:0] $end
$var reg 4 6 C [3:0] $end
$var reg 3 7 counter [2:0] $end
$upscope $end
$upscope $end
$upscope $end
$enddefinitions $end
#0
$dumpvars
b100 7
b0 6
b110 5
b111 4
b110 3
b0 2
b110 1
b111 0
b0 /
b100 .
b110 -
b100 ,
1+
b110 *
b0 )
b110 (
b111 '
0&
1%
b111 $
b110 #
0"
b110 !
$end
#5
0%
#10
0+
b1 )
b1 /
b1 2
1%
1&
#11
b1001 6
b11 ,
b11 .
b11 7
b10010011 !
b10010011 *
b10010011 -
b10010011 3
b11 5
#15
0%
#20
1+
b10 )
b10 /
b10 2
1%
#21
b1 ,
b1 .
b1 7
b101 6
b1010100 !
b1010100 *
b1010100 -
b1010100 3
b100 5
#25
0%
#30
0+
b1 )
b1 /
b1 2
1%
#31
b0 ,
b0 .
b0 7
b10 6
b101010 !
b101010 *
b101010 -
b101010 3
b1010 5
#35
0%
#40
1+
b0 )
b0 /
b0 2
1"
1%
#45
0%
#50
1%
#55
0%
#60
0"
b100 ,
b100 .
b100 7
b0 6
b11 !
b11 *
b11 -
b11 3
b11 5
b11 4
1%
b11 $
b11 '
b11 0
b11 #
b11 (
b11 1
0&
#65
0%
#70
0+
1%
1&
#71
b11010011 !
b11010011 *
b11010011 -
b11010011 3
b1101 6
#75
0%
#80
1+
b10 )
b10 /
b10 2
1%
#81
b10 ,
b10 .
b10 7
b10 6
b100100 !
b100100 *
b100100 -
b100100 3
b100 5
#85
0%
#90
0+
1%
#91
b0 ,
b0 .
b0 7
b0 6
b1001 !
b1001 *
b1001 -
b1001 3
b1001 5
#95
0%
#100
1+
b0 )
b0 /
b0 2
1"
1%
#105
0%
#110
1%
#115
0%
#120
0"
b100 ,
b100 .
b100 7
b1000 !
b1000 *
b1000 -
b1000 3
b1000 5
b101 4
1%
b101 $
b101 '
b101 0
b1000 #
b1000 (
b1000 1
0&
#125
0%
#130
0+
b11 )
b11 /
b11 2
1%
1&
#131
b1011 6
b1 ,
b1 .
b1 7
b10110001 !
b10110001 *
b10110001 -
b10110001 3
b1 5
#135
0%
#140
1+
b1 )
b1 /
b1 2
1%
#141
b0 ,
b0 .
b0 7
b10 6
b101000 !
b101000 *
b101000 -
b101000 3
b1000 5
#145
0%
#150
0+
b0 )
b0 /
b0 2
1"
1%
